bibsearch/__init__.py
bibsearch/_version.py
bibsearch/bibsearch.hy
bibsearch/cli.py
bibsearch/doi.hy
bibsearch/isbn.hy
hy_bibsearch-1.0.0.dist-info/LICENSE
hy_bibsearch-1.0.0.dist-info/METADATA
hy_bibsearch-1.0.0.dist-info/WHEEL
hy_bibsearch-1.0.0.dist-info/entry_points.txt
hy_bibsearch-1.0.0.dist-info/top_level.txt
hy_bibsearch-1.0.0.dist-info/RECORD
